LICENSE.txt
README.md
setup.py
aec/__init__.py
auto_env_config.egg-info/PKG-INFO
auto_env_config.egg-info/SOURCES.txt
auto_env_config.egg-info/dependency_links.txt
auto_env_config.egg-info/requires.txt
auto_env_config.egg-info/top_level.txt