Metadata-Version: 2.1
Name: auto-env-config
Version: 1.0.10
Summary: Configuring your python environment automatically.
Home-page: 
Author: 曾钦李
Author-email: 1838696034@qq.com
Maintainer: 
Maintainer-email: 
License: MIT License
Classifier: Topic :: Software Development :: Build Tools
Classifier: License :: OSI Approved :: MIT License
Classifier: Programming Language :: Python :: 3
Requires-Python: >=3.7
License-File: LICENSE.txt
